civic_data_identity_us_il/_version.py
civic_data_identity_us_il/make_chicago_identity_sample.py
civic_data_identity_us_il/py.typed
civic_data_identity_us_il-0.1.1.dist-info/licenses/LICENSE
civic_data_identity_us_il-0.1.1.dist-info/METADATA
civic_data_identity_us_il-0.1.1.dist-info/WHEEL
civic_data_identity_us_il-0.1.1.dist-info/top_level.txt
civic_data_identity_us_il-0.1.1.dist-info/RECORD
