Metadata-Version: 2.4
Name: civic-data-identity-us-il
Version: 0.1.1
Summary: Chicago open data used to validate CEP SNFEI.
Author-email: Civic Interconnect <info@civic-interconnect.org>
License-Expression: MIT
Project-URL: Data (index.json), https://raw.githubusercontent.com/civic-interconnect/civic-data-identity-us-il/refs/heads/main/data-out/index.json
Project-URL: Data (manifest.json), https://raw.githubusercontent.com/civic-interconnect/civic-data-identity-us-il/refs/heads/main/data-out/manifest.json
Project-URL: Documentation, https://civic-interconnect.github.io/civic-data-identity-us-il/latest
Project-URL: Homepage, https://github.com/civic-interconnect/civic-data-identity-us-il
Project-URL: Issues, https://github.com/civic-interconnect/civic-data-identity-us-il/issues
Project-URL: Source, https://github.com/civic-interconnect/civic-data-identity-us-il
Keywords: civic,US,Illinois
Classifier: Development Status :: 4 - Beta
Classifier: Intended Audience :: Developers
Classifier: Intended Audience :: Science/Research
Classifier: Intended Audience :: Education
Classifier: Natural Language :: English
Classifier: Operating System :: OS Independent
Classifier: Programming Language :: Python :: 3
Classifier: Programming Language :: Python :: 3 :: Only
Classifier: Programming Language :: Python :: 3.12
Classifier: Programming Language :: Python :: 3.13
Classifier: Topic :: Scientific/Engineering :: Information Analysis
Classifier: Typing :: Typed
Requires-Python: >=3.12
License-File: LICENSE
Requires-Dist: pandas
Provides-Extra: dev
Requires-Dist: build; extra == "dev"
Requires-Dist: pre-commit; extra == "dev"
Requires-Dist: pyright; extra == "dev"
Requires-Dist: pytest; extra == "dev"
Requires-Dist: pytest-cov; extra == "dev"
Requires-Dist: pytest-env; extra == "dev"
Requires-Dist: twine; extra == "dev"
Requires-Dist: validate-pyproject; extra == "dev"
Provides-Extra: docs
Requires-Dist: mike; extra == "docs"
Requires-Dist: mkdocs; extra == "docs"
Requires-Dist: mkdocs-gen-files; extra == "docs"
Requires-Dist: mkdocs-git-revision-date-localized-plugin; extra == "docs"
Requires-Dist: mkdocs-include-markdown-plugin; extra == "docs"
Requires-Dist: mkdocs-literate-nav; extra == "docs"
Requires-Dist: mkdocs-material; extra == "docs"
Requires-Dist: mkdocs-static-i18n; extra == "docs"
Requires-Dist: mkdocstrings[python]>=0.18; extra == "docs"
Requires-Dist: ruff; extra == "docs"
Dynamic: license-file
